inpynamodb/__init__.py
inpynamodb/indexes.py
inpynamodb/models.py
inpynamodb/pagination.py
inpynamodb/transactions.py
inpynamodb/connection/__init__.py
inpynamodb/connection/base.py
inpynamodb/connection/table.py
tests/__init__.py
tests/data.py
tests/deep_eq.py
tests/response.py
tests/test_base_connection.py
tests/test_model.py
tests/test_pagination.py
tests/test_table_connection.py
tests/test_transaction.py
InPynamoDB-4.1.3.dist-info/LICENSE
InPynamoDB-4.1.3.dist-info/METADATA
InPynamoDB-4.1.3.dist-info/WHEEL
InPynamoDB-4.1.3.dist-info/top_level.txt
InPynamoDB-4.1.3.dist-info/RECORD
