Metadata-Version: 2.1
Name: InPynamoDB
Version: 4.1.3
Summary: asyncio wrapper of PynamoDB
Home-page: https://github.com/sunghyun-lee/inpynamodb
Author: sunghyun-lee
Author-email: jolacaleb@gmail.com
License: MIT
Keywords: python dynamodb amazon async pynamodb
Platform: UNKNOWN
Classifier: Development Status :: 4 - Beta
Classifier: Intended Audience :: Developers
Classifier: Programming Language :: Python
Classifier: Operating System :: OS Independent
Classifier: Programming Language :: Python :: 3.6
Classifier: License :: OSI Approved :: MIT License
Requires-Dist: PynamoDB (==4.1.0)
Requires-Dist: aiobotocore (==0.10.3)
Requires-Dist: async-property (==0.2.1)
